setup.py
apple_search_ads.egg-info/PKG-INFO
apple_search_ads.egg-info/SOURCES.txt
apple_search_ads.egg-info/dependency_links.txt
apple_search_ads.egg-info/not-zip-safe
apple_search_ads.egg-info/requires.txt
apple_search_ads.egg-info/top_level.txt
search_ads/__init__.py
search_ads/api/__init__.py
search_ads/api/search_ads_building_blocks.py
search_ads/api/utils.py
search_ads/models/__init__.py
search_ads/models/reports.py
search_ads/models/store_models.py
search_ads/models/utils.py