Metadata-Version: 1.0
Name: apple-search-ads
Version: 0.2.7
Summary: Python wrapper for Apple Search Ads APIs
Home-page: https://github.com/aovlexus/apple-searchads-api
Author: Luca Giacomel forked by Aleksnadr Usov
Author-email: lg@bendingspoons.com, aovlexus@gmail.com
License: MIT
Platform: UNKNOWN
